vllm_rs-0.8.11.dist-info/METADATA
vllm_rs-0.8.11.dist-info/WHEEL
vllm_rs/ReadMe.md
vllm_rs/__init__.py
vllm_rs/__init__.pyi
vllm_rs/chat.py
vllm_rs/completion.py
vllm_rs/py.typed
vllm_rs/server.py
vllm_rs/vllm_rs.abi3.so
vllm_rs-0.8.11.dist-info/RECORD
