Metadata-Version: 2.4
Name: vllm-rs
Version: 0.8.11
